dtdt/__init__.py
dtdt/_types.py
dtdt/_version.py
dtdt/analysis.py
dtdt/loaders.py
dtdt-0.0.1.dist-info/LICENSE
dtdt-0.0.1.dist-info/METADATA
dtdt-0.0.1.dist-info/WHEEL
dtdt-0.0.1.dist-info/top_level.txt
dtdt-0.0.1.dist-info/RECORD
