Metadata-Version: 2.1
Name: dtdt
Version: 0.0.1
Summary: Dannys TDT - A typed implementation of the TDT API with some extra features.
Author-email: Daniel Alas <hi@danielalas.com>
Project-URL: Homepage, https://github.com/DannyAlas/dtdt
Project-URL: Issues, https://github.com/DannyAlas/dtdt/issues
Classifier: License :: OSI Approved :: MIT License
Classifier: Operating System :: OS Independent
Classifier: Programming Language :: Python :: 3 :: Only
Classifier: Programming Language :: Python :: 3.11
Classifier: Programming Language :: Python :: 3.12
Requires-Python: >=3.11
License-File: LICENSE
